MANIFEST.in
README.md
requirements-dev.txt
requirements.txt
setup.cfg
setup.py
cglims/__init__.py
cglims/api.py
cglims/apptag.py
cglims/check.py
cglims/config.py
cglims/constants.py
cglims/exc.py
cglims/export.py
cglims/panels.py
cglims/pedigree.py
cglims.egg-info/PKG-INFO
cglims.egg-info/SOURCES.txt
cglims.egg-info/dependency_links.txt
cglims.egg-info/entry_points.txt
cglims.egg-info/not-zip-safe
cglims.egg-info/requires.txt
cglims.egg-info/top_level.txt
cglims/cli/__init__.py
cglims/cli/base.py
cglims/cli/commands.py
cglims/cli/core.py
cglims/cli/log.py
cglims/cli/utils.py
tests/conftest.py
tests/test_api_samplesheetlims.py
tests/test_apptag.py
tests/test_pedigree.py