Metadata-Version: 1.1
Name: cglims
Version: 1.3.4
Summary: Microservice to interface with LIMS
Home-page: UNKNOWN
Author: Robin Andeer
Author-email: robin.andeer@scilifelab.se
License: BSD License
Keywords: pytest cli
Platform: any
Classifier: Development Status :: 3 - Alpha
Classifier: License :: OSI Approved :: BSD License
Classifier: Operating System :: OS Independent
Classifier: Programming Language :: Python
Classifier: Programming Language :: Python :: 2
Classifier: Programming Language :: Python :: 2.7
Classifier: Programming Language :: Python :: 3
Classifier: Programming Language :: Python :: 3.3
